{"assets":{"DFB2908B7CB4EB95DD219AA6E044D17C":{"type":"texture","index":5,"assetRequest":{"type":"slide","state":"contents","slide":"none"},"url":{"native":"assets\/88B5B4DA-368C-447D-A64F-D6888E9EF188.pdf"},"width":794,"height":1030},"016FC1301EAF50C4C6ACD022AFED12BD":{"type":"texture","index":3,"assetRequest":{"type":"slide","state":"contents","slide":"none"},"url":{"native":"assets\/88B5B4DA-368C-447D-A64F-D6888E9EF188.pdf"},"width":1017,"height":424},"C25C25FF361FB24FC35F6B120D2F252D":{"type":"texture","index":2,"assetRequest":{"type":"slide","state":"contents","slide":"none"},"url":{"native":"assets\/88B5B4DA-368C-447D-A64F-D6888E9EF188.pdf"},"width":1920,"height":1080},"BF09EC94DEE210DE0B8EB352295AAD0E":{"type":"texture","index":4,"assetRequest":{"type":"slide","state":"contents","slide":"none"},"url":{"native":"assets\/88B5B4DA-368C-447D-A64F-D6888E9EF188.pdf"},"width":1017,"height":593},"CF594FA0FF06A59A508F1F689ADD8AAE":{"type":"texture","index":6,"assetRequest":{"type":"slide","state":"contents","slide":"none"},"url":{"native":"assets\/88B5B4DA-368C-447D-A64F-D6888E9EF188.pdf"},"width":1900,"height":254},"9039E9FFE843538CB871DFC78CA9D073":{"type":"texture","index":0,"assetRequest":{"type":"slide","state":"contents","slide":"none"},"url":{"native":"assets\/88B5B4DA-368C-447D-A64F-D6888E9EF188.pdf"},"width":1920,"height":1080},"37AE089419EC3D8BC92D73092B9C0AC0":{"type":"texture","index":1,"assetRequest":{"type":"slide","state":"contents","slide":"none"},"url":{"native":"assets\/88B5B4DA-368C-447D-A64F-D6888E9EF188.pdf"},"width":1127,"height":133}},"events":[{"effects":[{"beginTime":0,"baseLayer":{"animations":[],"initialState":{"affineTransform":[1,0,0,1,0,0],"masksToBounds":false,"rotation":0,"scale":1,"position":{"pointX":659.5,"pointY":385.24999999999977},"width":1127,"sublayerTransform":[1,0,0,0,0,1,0,0,0,0,1,0,0,0,0,1],"contentsRect":{"y":0,"x":0,"width":1,"height":1},"opacity":1,"edgeAntialiasingMask":251658240,"height":133,"hidden":false,"anchorPoint":{"pointX":0.5,"pointY":0.5}},"objectID":"3DF25555-A96A-4D5A-9B92-EB6AC7310D51","layers":[{"animations":[],"initialState":{"affineTransform":[1,0,0,1,0,0],"masksToBounds":false,"rotation":0,"scale":1,"position":{"pointX":864,"pointY":221.25000000000023},"width":1127,"sublayerTransform":[1,0,0,0,0,1,0,0,0,0,1,-0.00035007912466775983,0,0,0,1],"contentsRect":{"y":0,"x":0,"width":1,"height":1},"opacity":1,"edgeAntialiasingMask":251658240,"height":133,"hidden":false,"anchorPoint":{"pointX":0.76663708961845611,"pointY":1.6635338345864679}},"layers":[{"animations":[{"additive":false,"timeOffset":0,"beginTime":1e-100,"repeatCount":0,"fillMode":"both","duration":2,"autoreverses":false,"animations":[{"additive":false,"timeOffset":0,"beginTime":0,"values":[{"scalar":-3065},{"scalar":-2710.2174017077427},{"scalar":-2383.9901162462925},{"scalar":-2082.5105344038284},{"scalar":-1803.8499727939122},{"scalar":-1546.6457662598516},{"scalar":-1309.877511779601},{"scalar":-1092.7884222694315},{"scalar":-894.85456182701591},{"scalar":-715.77805529238617},{"scalar":-555.49745474747169},{"scalar":-414.21477874317497},{"scalar":-292.4427078997054},{"scalar":-191.07973108941266},{"scalar":-111.52765733597519},{"scalar":-55.877894115427523},{"scalar":-27.216808177265648},{"scalar":-14.703412886849719},{"scalar":-4.3115533158929793},{"scalar":4.6160374488388243},{"scalar":12.731224859145414},{"scalar":20.684247301963069},{"scalar":29.127476543398416},{"scalar":38.719225371283983},{"scalar":50.127665286231377},{"scalar":77.026930371989693},{"scalar":130.18022306783331},{"scalar":206.80156182041978},{"scalar":304.99700650246075},{"scalar":423.50675935414506},{"scalar":561.54505892600628},{"scalar":718.69826814005023},{"scalar":894.8598660498684},{"scalar":1090.1905671000152},{"scalar":1305.0972653005115},{"scalar":1540.2282824281895},{"scalar":1796.4861838177853},{"scalar":2075.0658829268336},{"scalar":2377.5435988637719},{"scalar":2706.1190490598565},{"scalar":3065}],"repeatCount":0,"fillMode":"removed","duration":2,"autoreverses":false,"property":"transform.translation.x","keyTimes":[0,0.025000000000000001,0.050000000000000003,0.074999999999999997,0.10000000000000001,0.125,0.14999999999999999,0.17499999999999999,0.20000000000000001,0.22500000000000001,0.25,0.27500000000000002,0.29999999999999999,0.32500000000000001,0.34999999999999998,0.375,0.40000000000000002,0.42499999999999999,0.45000000000000001,0.47499999999999998,0.5,0.52500000000000002,0.55000000000000004,0.57499999999999996,0.59999999999999998,0.625,0.65000000000000002,0.67500000000000004,0.69999999999999996,0.72499999999999998,0.75,0.77500000000000002,0.80000000000000004,0.82499999999999996,0.84999999999999998,0.875,0.90000000000000002,0.92500000000000004,0.94999999999999996,0.97499999999999998,1],"removedOnCompletion":true},{"repeatCount":0,"removedOnCompletion":true,"timingFunctions":[{"timingFunction":"Linear"},{"timingFunction":"custom","timingControlPoint1y":0,"timingControlPoint2x":0.58196371793746948,"timingControlPoint1x":0,"timingControlPoint2y":1},{"timingFunction":"Linear"},{"timingFunction":"custom","timingControlPoint1y":0,"timingControlPoint2x":1,"timingControlPoint1x":0.42485535144805908,"timingControlPoint2y":1},{"timingFunction":"Linear"}],"keyTimes":[0,0,0.33333333333333331,0.66666666666666663,1,1],"additive":false,"values":[{"scalar":0},{"scalar":0},{"scalar":1},{"scalar":1},{"scalar":0},{"scalar":0}],"timeOffset":0,"autoreverses":false,"property":"opacity","fillMode":"both","duration":2,"beginTime":0},{"additive":false,"timeOffset":0,"beginTime":3.3333333333333335e-05,"from":{"scalar":0},"repeatCount":0,"fillMode":"forwards","duration":1.9999666666666667,"autoreverses":false,"property":"hidden","to":{"scalar":0},"removedOnCompletion":true}],"removedOnCompletion":false}],"layers":[],"texturedRectangle":{"singleTextureOpacity":1,"textXHeight":0.54842105263157903,"textBaseline":0.84097358875704886,"isBackgroundTexture":true,"isVerticalText":false,"textColor":[0.99991613626480103,1,0.99988490343093872,1],"textureType":6},"initialState":{"affineTransform":[1,0,0,1,0,0],"masksToBounds":false,"rotation":0,"scale":1,"position":{"pointX":581.5,"pointY":229.75000000000023},"width":1127,"sublayerTransform":[1,0,0,0,0,1,0,0,0,0,1,0,0,0,0,1],"contentsRect":{"y":0,"x":0,"width":1,"height":1},"opacity":1,"edgeAntialiasingMask":0,"height":133,"hidden":true,"anchorPoint":{"pointX":0.5,"pointY":0.5}},"texture":"37AE089419EC3D8BC92D73092B9C0AC0"}]}]},"effects":[],"duration":2,"type":"buildIn","attributes":{"direction":11},"name":"apple:drift","objectID":"3DF25555-A96A-4D5A-9B92-EB6AC7310D51"}],"automaticPlay":false,"hyperlinks":[],"accessibility":[],"baseLayer":{"animations":[],"initialState":{"affineTransform":[1,0,0,1,0,0],"masksToBounds":false,"rotation":0,"scale":1,"position":{"pointX":960,"pointY":540},"width":1920,"sublayerTransform":[1,0,0,0,0,1,0,0,0,0,1,0,0,0,0,1],"contentsRect":{"y":0,"x":0,"width":1,"height":1},"opacity":1,"edgeAntialiasingMask":251658240,"height":1080,"hidden":false,"anchorPoint":{"pointX":0.5,"pointY":0.5}},"layers":[{"animations":[],"initialState":{"affineTransform":[1,0,0,1,0,0],"masksToBounds":false,"rotation":0,"scale":1,"position":{"pointX":960,"pointY":540},"width":1920,"sublayerTransform":[1,0,0,0,0,1,0,0,0,0,1,0,0,0,0,1],"contentsRect":{"y":0,"x":0,"width":1,"height":1},"opacity":1,"edgeAntialiasingMask":251658240,"height":1080,"hidden":false,"anchorPoint":{"pointX":0.5,"pointY":0.5}},"layers":[{"animations":[],"initialState":{"affineTransform":[1,0,0,1,0,0],"masksToBounds":false,"rotation":0,"scale":1,"position":{"pointX":960,"pointY":540},"width":1920,"sublayerTransform":[1,0,0,0,0,1,0,0,0,0,1,0,0,0,0,1],"contentsRect":{"y":0,"x":0,"width":1,"height":1},"opacity":1,"edgeAntialiasingMask":251658240,"height":1080,"hidden":false,"anchorPoint":{"pointX":0.5,"pointY":0.5}},"layers":[{"animations":[],"layers":[],"texturedRectangle":{"isBackgroundTexture":true,"singleTextureOpacity":1,"textureType":1,"textBaseline":0,"textXHeight":0,"isVerticalText":false},"initialState":{"affineTransform":[1,0,0,1,0,0],"masksToBounds":false,"rotation":0,"scale":1,"position":{"pointX":960,"pointY":540},"width":1920,"sublayerTransform":[1,0,0,0,0,1,0,0,0,0,1,0,0,0,0,1],"contentsRect":{"y":0,"x":0,"width":1,"height":1},"opacity":1,"edgeAntialiasingMask":0,"height":1080,"hidden":false,"anchorPoint":{"pointX":0.5,"pointY":0.5}},"texture":"9039E9FFE843538CB871DFC78CA9D073"}]}]},{"animations":[],"initialState":{"affineTransform":[1,0,0,1,0,0],"masksToBounds":false,"rotation":0,"scale":1,"position":{"pointX":960,"pointY":540},"width":1920,"sublayerTransform":[1,0,0,0,0,1,0,0,0,0,1,0,0,0,0,1],"contentsRect":{"y":0,"x":0,"width":1,"height":1},"opacity":1,"edgeAntialiasingMask":251658240,"height":1080,"hidden":false,"anchorPoint":{"pointX":0.5,"pointY":0.5}},"layers":[{"animations":[],"initialState":{"affineTransform":[1,0,0,1,0,0],"masksToBounds":false,"rotation":0,"scale":1,"position":{"pointX":659.5,"pointY":385.24999999999977},"width":1127,"sublayerTransform":[1,0,0,0,0,1,0,0,0,0,1,0,0,0,0,1],"contentsRect":{"y":0,"x":0,"width":1,"height":1},"opacity":1,"edgeAntialiasingMask":251658240,"height":133,"hidden":false,"anchorPoint":{"pointX":0.5,"pointY":0.5}},"objectID":"3DF25555-A96A-4D5A-9B92-EB6AC7310D51","layers":[{"animations":[],"layers":[],"texturedRectangle":{"singleTextureOpacity":1,"textXHeight":0.54842105263157903,"textBaseline":0.84097358875704886,"isBackgroundTexture":true,"isVerticalText":false,"textColor":[0.99991613626480103,1,0.99988490343093872,1],"textureType":6},"initialState":{"affineTransform":[1,0,0,1,0,0],"masksToBounds":false,"rotation":0,"scale":1,"position":{"pointX":581.5,"pointY":229.75000000000023},"width":1127,"sublayerTransform":[1,0,0,0,0,1,0,0,0,0,1,0,0,0,0,1],"contentsRect":{"y":0,"x":0,"width":1,"height":1},"opacity":1,"edgeAntialiasingMask":0,"height":133,"hidden":true,"anchorPoint":{"pointX":0.5,"pointY":0.5}},"texture":"37AE089419EC3D8BC92D73092B9C0AC0"}]}]}]}},{"effects":[{"beginTime":0,"baseLayer":{"animations":[],"initialState":{"affineTransform":[1,0,0,1,0,0],"masksToBounds":false,"rotation":0,"scale":1,"position":{"pointX":960,"pointY":540},"width":1920,"sublayerTransform":[1,0,0,0,0,1,0,0,0,0,1,0,0,0,0,1],"contentsRect":{"y":0,"x":0,"width":1,"height":1},"opacity":1,"edgeAntialiasingMask":251658240,"height":1080,"hidden":false,"anchorPoint":{"pointX":0.5,"pointY":0.5}},"objectID":"0","layers":[{"animations":[],"initialState":{"affineTransform":[1,0,0,1,0,0],"masksToBounds":false,"rotation":0,"scale":1,"position":{"pointX":960,"pointY":540},"width":1920,"sublayerTransform":[1,0,0,0,0,1,0,0,0,0,1,-0.00035007912466775983,0,0,0,1],"contentsRect":{"y":0,"x":0,"width":1,"height":1},"opacity":1,"edgeAntialiasingMask":251658240,"height":1080,"hidden":false,"anchorPoint":{"pointX":0.5,"pointY":0.5}},"layers":[{"animations":[],"initialState":{"affineTransform":[1,0,0,1,0,0],"masksToBounds":false,"rotation":0,"scale":1,"position":{"pointX":960,"pointY":540},"width":1920,"sublayerTransform":[1,0,0,0,0,1,0,0,0,0,1,0,0,0,0,1],"contentsRect":{"y":0,"x":0,"width":1,"height":1},"opacity":1,"edgeAntialiasingMask":251658240,"height":1080,"hidden":false,"anchorPoint":{"pointX":0.5,"pointY":0.5}},"layers":[{"animations":[{"repeatCount":0,"removedOnCompletion":false,"from":{"scalar":false},"timingFunction":"EaseInEaseOut","additive":false,"timeOffset":0,"autoreverses":false,"property":"hidden","fillMode":"both","duration":2,"beginTime":0,"to":{"scalar":false}}],"layers":[],"texturedRectangle":{"isBackgroundTexture":true,"singleTextureOpacity":1,"textureType":1,"textBaseline":0,"textXHeight":0,"isVerticalText":false},"initialState":{"affineTransform":[1,0,0,1,0,0],"masksToBounds":false,"rotation":0,"scale":1,"position":{"pointX":960,"pointY":540},"width":1920,"sublayerTransform":[1,0,0,0,0,1,0,0,0,0,1,0,0,0,0,1],"contentsRect":{"y":0,"x":0,"width":1,"height":1},"opacity":1,"edgeAntialiasingMask":0,"height":1080,"hidden":false,"anchorPoint":{"pointX":0.5,"pointY":0.5}},"texture":"C25C25FF361FB24FC35F6B120D2F252D"}]},{"animations":[],"initialState":{"affineTransform":[1,0,0,1,0,0],"masksToBounds":false,"rotation":0,"scale":1,"position":{"pointX":960,"pointY":540},"width":1920,"sublayerTransform":[1,0,0,0,0,1,0,0,0,0,1,0,0,0,0,1],"contentsRect":{"y":0,"x":0,"width":1,"height":1},"opacity":1,"edgeAntialiasingMask":251658240,"height":1080,"hidden":false,"anchorPoint":{"pointX":0.5,"pointY":0.5}},"layers":[{"animations":[{"repeatCount":0,"removedOnCompletion":false,"from":{"scalar":1},"timingFunction":"EaseInEaseOut","additive":false,"timeOffset":0,"autoreverses":false,"property":"opacity","fillMode":"both","duration":2,"beginTime":0,"to":{"scalar":0}}],"layers":[],"texturedRectangle":{"isBackgroundTexture":true,"singleTextureOpacity":1,"textureType":1,"textBaseline":0,"textXHeight":0,"isVerticalText":false},"initialState":{"affineTransform":[1,0,0,1,0,0],"masksToBounds":false,"rotation":0,"scale":1,"position":{"pointX":960,"pointY":540},"width":1920,"sublayerTransform":[1,0,0,0,0,1,0,0,0,0,1,0,0,0,0,1],"contentsRect":{"y":0,"x":0,"width":1,"height":1},"opacity":1,"edgeAntialiasingMask":0,"height":1080,"hidden":false,"anchorPoint":{"pointX":0.5,"pointY":0.5}},"texture":"9039E9FFE843538CB871DFC78CA9D073"}]}]},{"animations":[],"initialState":{"affineTransform":[1,0,0,1,0,0],"masksToBounds":false,"rotation":0,"scale":1,"position":{"pointX":558.5,"pointY":818},"width":1017,"sublayerTransform":[1,0,0,0,0,1,0,0,0,0,1,0,0,0,0,1],"contentsRect":{"y":0,"x":0,"width":1,"height":1},"opacity":1,"edgeAntialiasingMask":251658240,"height":424,"hidden":false,"anchorPoint":{"pointX":0.5,"pointY":0.5}},"layers":[{"animations":[{"additive":false,"timeOffset":0,"beginTime":0,"repeatCount":0,"fillMode":"both","duration":2,"autoreverses":false,"animations":[{"repeatCount":0,"removedOnCompletion":true,"from":{"pointX":2427.5,"pointY":211},"timingFunction":"EaseInEaseOut","additive":false,"timeOffset":0,"autoreverses":false,"property":"position","fillMode":"both","duration":2,"beginTime":0,"to":{"pointX":507.5,"pointY":211}},{"additive":false,"timeOffset":0,"beginTime":0,"from":{"scalar":1},"repeatCount":0,"fillMode":"both","duration":2,"autoreverses":false,"property":"opacity","to":{"scalar":1},"removedOnCompletion":true},{"additive":false,"timeOffset":0,"beginTime":0,"from":{"scalar":false},"repeatCount":0,"fillMode":"both","duration":2,"autoreverses":false,"property":"hidden","to":{"scalar":false},"removedOnCompletion":true}],"removedOnCompletion":false}],"layers":[],"texturedRectangle":{"isBackgroundTexture":true,"singleTextureOpacity":1,"textureType":5,"textBaseline":0,"textXHeight":0,"isVerticalText":false},"initialState":{"affineTransform":[1,0,0,1,0,0],"masksToBounds":false,"rotation":0,"scale":1,"position":{"pointX":507.5,"pointY":211},"width":1017,"sublayerTransform":[1,0,0,0,0,1,0,0,0,0,1,0,0,0,0,1],"contentsRect":{"y":0,"x":0,"width":1,"height":1},"opacity":1,"edgeAntialiasingMask":0,"height":424,"hidden":true,"anchorPoint":{"pointX":0.5,"pointY":0.5}},"texture":"016FC1301EAF50C4C6ACD022AFED12BD"}]},{"animations":[],"initialState":{"affineTransform":[1,0,0,1,0,0],"masksToBounds":false,"rotation":0,"scale":1,"position":{"pointX":558.5,"pointY":296.5},"width":1017,"sublayerTransform":[1,0,0,0,0,1,0,0,0,0,1,0,0,0,0,1],"contentsRect":{"y":0,"x":0,"width":1,"height":1},"opacity":1,"edgeAntialiasingMask":251658240,"height":593,"hidden":false,"anchorPoint":{"pointX":0.5,"pointY":0.5}},"layers":[{"animations":[{"additive":false,"timeOffset":0,"beginTime":0,"repeatCount":0,"fillMode":"both","duration":2,"autoreverses":false,"animations":[{"repeatCount":0,"removedOnCompletion":true,"from":{"pointX":3067.5,"pointY":295.5},"timingFunction":"EaseInEaseOut","additive":false,"timeOffset":0,"autoreverses":false,"property":"position","fillMode":"both","duration":2,"beginTime":0,"to":{"pointX":507.5,"pointY":295.5}},{"additive":false,"timeOffset":0,"beginTime":0,"from":{"scalar":1},"repeatCount":0,"fillMode":"both","duration":2,"autoreverses":false,"property":"opacity","to":{"scalar":1},"removedOnCompletion":true},{"additive":false,"timeOffset":0,"beginTime":0,"from":{"scalar":false},"repeatCount":0,"fillMode":"both","duration":2,"autoreverses":false,"property":"hidden","to":{"scalar":false},"removedOnCompletion":true}],"removedOnCompletion":false}],"layers":[],"texturedRectangle":{"isBackgroundTexture":true,"singleTextureOpacity":1,"textureType":5,"textBaseline":0,"textXHeight":0,"isVerticalText":false},"initialState":{"affineTransform":[1,0,0,1,0,0],"masksToBounds":false,"rotation":0,"scale":1,"position":{"pointX":507.5,"pointY":295.5},"width":1017,"sublayerTransform":[1,0,0,0,0,1,0,0,0,0,1,0,0,0,0,1],"contentsRect":{"y":0,"x":0,"width":1,"height":1},"opacity":1,"edgeAntialiasingMask":0,"height":593,"hidden":true,"anchorPoint":{"pointX":0.5,"pointY":0.5}},"texture":"BF09EC94DEE210DE0B8EB352295AAD0E"}]},{"animations":[],"initialState":{"affineTransform":[1,0,0,1,0,0],"masksToBounds":false,"rotation":0,"scale":1,"position":{"pointX":1476.9999809265137,"pointY":515},"width":794,"sublayerTransform":[1,0,0,0,0,1,0,0,0,0,1,0,0,0,0,1],"contentsRect":{"y":0,"x":0,"width":1,"height":1},"opacity":1,"edgeAntialiasingMask":251658240,"height":1030,"hidden":false,"anchorPoint":{"pointX":0.5,"pointY":0.5}},"layers":[{"animations":[{"additive":false,"timeOffset":0,"beginTime":0,"repeatCount":0,"fillMode":"both","duration":2,"autoreverses":false,"animations":[{"repeatCount":0,"removedOnCompletion":true,"from":{"pointX":3595.0000190734859,"pointY":514},"timingFunction":"EaseInEaseOut","additive":false,"timeOffset":0,"autoreverses":false,"property":"position","fillMode":"both","duration":2,"beginTime":0,"to":{"pointX":395.00001907348633,"pointY":514}},{"additive":false,"timeOffset":0,"beginTime":0,"from":{"scalar":1},"repeatCount":0,"fillMode":"both","duration":2,"autoreverses":false,"property":"opacity","to":{"scalar":1},"removedOnCompletion":true},{"additive":false,"timeOffset":0,"beginTime":0,"from":{"scalar":false},"repeatCount":0,"fillMode":"both","duration":2,"autoreverses":false,"property":"hidden","to":{"scalar":false},"removedOnCompletion":true}],"removedOnCompletion":false}],"layers":[],"texturedRectangle":{"isBackgroundTexture":true,"singleTextureOpacity":1,"textureType":5,"textBaseline":0,"textXHeight":0,"isVerticalText":false},"initialState":{"affineTransform":[1,0,0,1,0,0],"masksToBounds":false,"rotation":0,"scale":1,"position":{"pointX":395.00001907348633,"pointY":514},"width":794,"sublayerTransform":[1,0,0,0,0,1,0,0,0,0,1,0,0,0,0,1],"contentsRect":{"y":0,"x":0,"width":1,"height":1},"opacity":1,"edgeAntialiasingMask":0,"height":1030,"hidden":true,"anchorPoint":{"pointX":0.5,"pointY":0.5}},"texture":"DFB2908B7CB4EB95DD219AA6E044D17C"}]},{"animations":[],"initialState":{"affineTransform":[1,0,0,1,0,0],"masksToBounds":false,"rotation":0,"scale":1,"position":{"pointX":961.70001983642578,"pointY":893.4006290435791},"width":1900,"sublayerTransform":[1,0,0,0,0,1,0,0,0,0,1,0,0,0,0,1],"contentsRect":{"y":0,"x":0,"width":1,"height":1},"opacity":1,"edgeAntialiasingMask":251658240,"height":254,"hidden":false,"anchorPoint":{"pointX":0.5,"pointY":0.5}},"layers":[{"animations":[{"additive":false,"timeOffset":0,"beginTime":0,"repeatCount":0,"fillMode":"both","duration":2,"autoreverses":false,"animations":[{"repeatCount":0,"removedOnCompletion":true,"from":{"pointX":4788.2999801635742,"pointY":125.5993709564209},"timingFunction":"EaseInEaseOut","additive":false,"timeOffset":0,"autoreverses":false,"property":"position","fillMode":"both","duration":2,"beginTime":0,"to":{"pointX":948.29998016357422,"pointY":125.5993709564209}},{"additive":false,"timeOffset":0,"beginTime":0,"from":{"scalar":1},"repeatCount":0,"fillMode":"both","duration":2,"autoreverses":false,"property":"opacity","to":{"scalar":1},"removedOnCompletion":true},{"additive":false,"timeOffset":0,"beginTime":0,"from":{"scalar":false},"repeatCount":0,"fillMode":"both","duration":2,"autoreverses":false,"property":"hidden","to":{"scalar":false},"removedOnCompletion":true}],"removedOnCompletion":false}],"layers":[],"texturedRectangle":{"singleTextureOpacity":1,"textXHeight":0,"shapePath":{"lineWidth":1,"flatness":0.59999999999999998,"lineCapStyle":0,"elements":[{"type":"MoveToPoint","points":[[1.7000198364257812,1.4006290435791016]]},{"type":"AddLine","points":[[1898.2999801635742,1.4006290435791016]]},{"type":"AddLine","points":[[1898.2999801635742,252.8009090423584]]},{"type":"AddLine","points":[[1.7000198364257812,252.8009090423584]]},{"type":"CloseSubpath"},{"type":"MoveToPoint","points":[[1.7000198364257812,1.4006290435791016]]}],"windingRule":0,"lineJoinStyle":0,"miterLimit":10},"isBackgroundTexture":true,"textBaseline":0,"isVerticalText":false,"textureType":5},"initialState":{"affineTransform":[1,0,0,1,0,0],"masksToBounds":false,"rotation":0,"scale":1,"position":{"pointX":948.29998016357422,"pointY":125.5993709564209},"width":1900,"sublayerTransform":[1,0,0,0,0,1,0,0,0,0,1,0,0,0,0,1],"contentsRect":{"y":0,"x":0,"width":1,"height":1},"opacity":1,"edgeAntialiasingMask":0,"height":254,"hidden":true,"anchorPoint":{"pointX":0.5,"pointY":0.5}},"texture":"CF594FA0FF06A59A508F1F689ADD8AAE"}]}]},"effects":[],"duration":2,"type":"transition","attributes":{"direction":12},"name":"apple:ca-push","objectID":"0"}],"automaticPlay":false,"hyperlinks":[],"accessibility":[],"baseLayer":{"animations":[],"initialState":{"affineTransform":[1,0,0,1,0,0],"masksToBounds":false,"rotation":0,"scale":1,"position":{"pointX":960,"pointY":540},"width":1920,"sublayerTransform":[1,0,0,0,0,1,0,0,0,0,1,0,0,0,0,1],"contentsRect":{"y":0,"x":0,"width":1,"height":1},"opacity":1,"edgeAntialiasingMask":251658240,"height":1080,"hidden":false,"anchorPoint":{"pointX":0.5,"pointY":0.5}},"objectID":"0","layers":[{"animations":[],"initialState":{"affineTransform":[1,0,0,1,0,0],"masksToBounds":false,"rotation":0,"scale":1,"position":{"pointX":960,"pointY":540},"width":1920,"sublayerTransform":[1,0,0,0,0,1,0,0,0,0,1,-0.00035007912466775983,0,0,0,1],"contentsRect":{"y":0,"x":0,"width":1,"height":1},"opacity":1,"edgeAntialiasingMask":251658240,"height":1080,"hidden":false,"anchorPoint":{"pointX":0.5,"pointY":0.5}},"layers":[{"animations":[],"initialState":{"affineTransform":[1,0,0,1,0,0],"masksToBounds":false,"rotation":0,"scale":1,"position":{"pointX":960,"pointY":540},"width":1920,"sublayerTransform":[1,0,0,0,0,1,0,0,0,0,1,0,0,0,0,1],"contentsRect":{"y":0,"x":0,"width":1,"height":1},"opacity":1,"edgeAntialiasingMask":251658240,"height":1080,"hidden":false,"anchorPoint":{"pointX":0.5,"pointY":0.5}},"layers":[{"animations":[],"layers":[],"texturedRectangle":{"isBackgroundTexture":true,"singleTextureOpacity":1,"textureType":1,"textBaseline":0,"textXHeight":0,"isVerticalText":false},"initialState":{"affineTransform":[1,0,0,1,0,0],"masksToBounds":false,"rotation":0,"scale":1,"position":{"pointX":960,"pointY":540},"width":1920,"sublayerTransform":[1,0,0,0,0,1,0,0,0,0,1,0,0,0,0,1],"contentsRect":{"y":0,"x":0,"width":1,"height":1},"opacity":1,"edgeAntialiasingMask":0,"height":1080,"hidden":false,"anchorPoint":{"pointX":0.5,"pointY":0.5}},"texture":"C25C25FF361FB24FC35F6B120D2F252D"}]},{"animations":[],"initialState":{"affineTransform":[1,0,0,1,0,0],"masksToBounds":false,"rotation":0,"scale":1,"position":{"pointX":960,"pointY":540},"width":1920,"sublayerTransform":[1,0,0,0,0,1,0,0,0,0,1,0,0,0,0,1],"contentsRect":{"y":0,"x":0,"width":1,"height":1},"opacity":1,"edgeAntialiasingMask":251658240,"height":1080,"hidden":false,"anchorPoint":{"pointX":0.5,"pointY":0.5}},"layers":[{"animations":[],"layers":[],"texturedRectangle":{"isBackgroundTexture":true,"singleTextureOpacity":1,"textureType":1,"textBaseline":0,"textXHeight":0,"isVerticalText":false},"initialState":{"affineTransform":[1,0,0,1,0,0],"masksToBounds":false,"rotation":0,"scale":1,"position":{"pointX":960,"pointY":540},"width":1920,"sublayerTransform":[1,0,0,0,0,1,0,0,0,0,1,0,0,0,0,1],"contentsRect":{"y":0,"x":0,"width":1,"height":1},"opacity":1,"edgeAntialiasingMask":0,"height":1080,"hidden":false,"anchorPoint":{"pointX":0.5,"pointY":0.5}},"texture":"9039E9FFE843538CB871DFC78CA9D073"}]}]},{"animations":[],"initialState":{"affineTransform":[1,0,0,1,0,0],"masksToBounds":false,"rotation":0,"scale":1,"position":{"pointX":558.5,"pointY":818},"width":1017,"sublayerTransform":[1,0,0,0,0,1,0,0,0,0,1,0,0,0,0,1],"contentsRect":{"y":0,"x":0,"width":1,"height":1},"opacity":1,"edgeAntialiasingMask":251658240,"height":424,"hidden":false,"anchorPoint":{"pointX":0.5,"pointY":0.5}},"layers":[{"animations":[],"layers":[],"texturedRectangle":{"isBackgroundTexture":true,"singleTextureOpacity":1,"textureType":5,"textBaseline":0,"textXHeight":0,"isVerticalText":false},"initialState":{"affineTransform":[1,0,0,1,0,0],"masksToBounds":false,"rotation":0,"scale":1,"position":{"pointX":507.5,"pointY":211},"width":1017,"sublayerTransform":[1,0,0,0,0,1,0,0,0,0,1,0,0,0,0,1],"contentsRect":{"y":0,"x":0,"width":1,"height":1},"opacity":1,"edgeAntialiasingMask":0,"height":424,"hidden":true,"anchorPoint":{"pointX":0.5,"pointY":0.5}},"texture":"016FC1301EAF50C4C6ACD022AFED12BD"}]},{"animations":[],"initialState":{"affineTransform":[1,0,0,1,0,0],"masksToBounds":false,"rotation":0,"scale":1,"position":{"pointX":558.5,"pointY":296.5},"width":1017,"sublayerTransform":[1,0,0,0,0,1,0,0,0,0,1,0,0,0,0,1],"contentsRect":{"y":0,"x":0,"width":1,"height":1},"opacity":1,"edgeAntialiasingMask":251658240,"height":593,"hidden":false,"anchorPoint":{"pointX":0.5,"pointY":0.5}},"layers":[{"animations":[],"layers":[],"texturedRectangle":{"isBackgroundTexture":true,"singleTextureOpacity":1,"textureType":5,"textBaseline":0,"textXHeight":0,"isVerticalText":false},"initialState":{"affineTransform":[1,0,0,1,0,0],"masksToBounds":false,"rotation":0,"scale":1,"position":{"pointX":507.5,"pointY":295.5},"width":1017,"sublayerTransform":[1,0,0,0,0,1,0,0,0,0,1,0,0,0,0,1],"contentsRect":{"y":0,"x":0,"width":1,"height":1},"opacity":1,"edgeAntialiasingMask":0,"height":593,"hidden":true,"anchorPoint":{"pointX":0.5,"pointY":0.5}},"texture":"BF09EC94DEE210DE0B8EB352295AAD0E"}]},{"animations":[],"initialState":{"affineTransform":[1,0,0,1,0,0],"masksToBounds":false,"rotation":0,"scale":1,"position":{"pointX":1476.9999809265137,"pointY":515},"width":794,"sublayerTransform":[1,0,0,0,0,1,0,0,0,0,1,0,0,0,0,1],"contentsRect":{"y":0,"x":0,"width":1,"height":1},"opacity":1,"edgeAntialiasingMask":251658240,"height":1030,"hidden":false,"anchorPoint":{"pointX":0.5,"pointY":0.5}},"layers":[{"animations":[],"layers":[],"texturedRectangle":{"isBackgroundTexture":true,"singleTextureOpacity":1,"textureType":5,"textBaseline":0,"textXHeight":0,"isVerticalText":false},"initialState":{"affineTransform":[1,0,0,1,0,0],"masksToBounds":false,"rotation":0,"scale":1,"position":{"pointX":395.00001907348633,"pointY":514},"width":794,"sublayerTransform":[1,0,0,0,0,1,0,0,0,0,1,0,0,0,0,1],"contentsRect":{"y":0,"x":0,"width":1,"height":1},"opacity":1,"edgeAntialiasingMask":0,"height":1030,"hidden":true,"anchorPoint":{"pointX":0.5,"pointY":0.5}},"texture":"DFB2908B7CB4EB95DD219AA6E044D17C"}]},{"animations":[],"initialState":{"affineTransform":[1,0,0,1,0,0],"masksToBounds":false,"rotation":0,"scale":1,"position":{"pointX":961.70001983642578,"pointY":893.4006290435791},"width":1900,"sublayerTransform":[1,0,0,0,0,1,0,0,0,0,1,0,0,0,0,1],"contentsRect":{"y":0,"x":0,"width":1,"height":1},"opacity":1,"edgeAntialiasingMask":251658240,"height":254,"hidden":false,"anchorPoint":{"pointX":0.5,"pointY":0.5}},"layers":[{"animations":[],"layers":[],"texturedRectangle":{"singleTextureOpacity":1,"textXHeight":0,"shapePath":{"lineWidth":1,"flatness":0.59999999999999998,"lineCapStyle":0,"elements":[{"type":"MoveToPoint","points":[[1.7000198364257812,1.4006290435791016]]},{"type":"AddLine","points":[[1898.2999801635742,1.4006290435791016]]},{"type":"AddLine","points":[[1898.2999801635742,252.8009090423584]]},{"type":"AddLine","points":[[1.7000198364257812,252.8009090423584]]},{"type":"CloseSubpath"},{"type":"MoveToPoint","points":[[1.7000198364257812,1.4006290435791016]]}],"windingRule":0,"lineJoinStyle":0,"miterLimit":10},"isBackgroundTexture":true,"textBaseline":0,"isVerticalText":false,"textureType":5},"initialState":{"affineTransform":[1,0,0,1,0,0],"masksToBounds":false,"rotation":0,"scale":1,"position":{"pointX":948.29998016357422,"pointY":125.5993709564209},"width":1900,"sublayerTransform":[1,0,0,0,0,1,0,0,0,0,1,0,0,0,0,1],"contentsRect":{"y":0,"x":0,"width":1,"height":1},"opacity":1,"edgeAntialiasingMask":0,"height":254,"hidden":true,"anchorPoint":{"pointX":0.5,"pointY":0.5}},"texture":"CF594FA0FF06A59A508F1F689ADD8AAE"}]}]}}]}